commands.yaml
ccmd/__init__.py
ccmd/cli/__init__.py
ccmd/cli/editor.py
ccmd/cli/install.py
ccmd/cli/interactive.py
ccmd/cli/main.py
ccmd/cli/ssh_manager.py
ccmd/core/__init__.py
ccmd/core/auth.py
ccmd/core/executor.py
ccmd/core/parser.py
ccmd/core/registry.py
ccmd/core/rollback.py
ccmd/core/security.py
ccmd/core/system_check.py
ccmd-1.1.7.dist-info/licenses/LICENSE
ccmd-1.1.7.dist-info/METADATA
ccmd-1.1.7.dist-info/WHEEL
ccmd-1.1.7.dist-info/entry_points.txt
ccmd-1.1.7.dist-info/top_level.txt
ccmd-1.1.7.dist-info/RECORD
