Metadata-Version: 2.4
Name: ccmd
Version: 1.1.7
Summary: Cross-platform Command Manager - Simplify your terminal with intuitive shortcuts
Author-email: De Catalyst <Robert5560newton@gmail.com>
Maintainer-email: De Catalyst <Robert5560newton@gmail.com>
License: MIT
Project-URL: Homepage, https://github.com/Wisyle/ccmd
Project-URL: Documentation, https://github.com/Wisyle/ccmd#readme
Project-URL: Repository, https://github.com/Wisyle/ccmd
Project-URL: Bug Tracker, https://github.com/Wisyle/ccmd/issues
Project-URL: Security, https://github.com/Wisyle/ccmd/security
Project-URL: Changelog, https://github.com/Wisyle/ccmd/releases
Keywords: cli,command-line,terminal,productivity,automation,shell,commands,shortcuts,developer-tools,cross-platform
Classifier: Development Status :: 5 - Production/Stable
Classifier: Environment :: Console
Classifier: Intended Audience :: Developers
Classifier: Intended Audience :: System Administrators
Classifier: License :: OSI Approved :: MIT License
Classifier: Operating System :: OS Independent
Classifier: Operating System :: POSIX :: Linux
Classifier: Operating System :: MacOS
Classifier: Operating System :: Microsoft :: Windows
Classifier: Programming Language :: Python :: 3
Classifier: Programming Language :: Python :: 3.7
Classifier: Programming Language :: Python :: 3.8
Classifier: Programming Language :: Python :: 3.9
Classifier: Programming Language :: Python :: 3.10
Classifier: Programming Language :: Python :: 3.11
Classifier: Programming Language :: Python :: 3.12
Classifier: Topic :: Software Development
Classifier: Topic :: System :: Shells
Classifier: Topic :: System :: System Shells
Classifier: Topic :: Utilities
Requires-Python: >=3.7
License-File: LICENSE
Requires-Dist: PyYAML>=6.0
Requires-Dist: questionary>=2.0.0
Requires-Dist: GitPython==3.1.45
Requires-Dist: bcrypt>=4.0.0
Provides-Extra: dev
Requires-Dist: pytest>=7.0; extra == "dev"
Requires-Dist: pytest-cov>=4.0; extra == "dev"
Requires-Dist: bandit>=1.7; extra == "dev"
Requires-Dist: safety>=2.0; extra == "dev"
Dynamic: license-file
